README.rst
setup.py
django_braintree/__init__.py
django_braintree/admin.py
django_braintree/forms.py
django_braintree/models.py
django_braintree/test_settings.py
django_braintree/tests.py
django_braintree/urls.py
django_braintree/views.py
tivix_django_braintree.egg-info/PKG-INFO
tivix_django_braintree.egg-info/SOURCES.txt
tivix_django_braintree.egg-info/dependency_links.txt
tivix_django_braintree.egg-info/not-zip-safe
tivix_django_braintree.egg-info/requires.txt
tivix_django_braintree.egg-info/top_level.txt