Metadata-Version: 1.0
Name: tivix-django-braintree
Version: 0.1.2
Summary: An easy way to integrate with Braintree Payment Solutions from Django.
Home-page: http://github.com/tivix/django-braintree
Author: Sumit Chachra
Author-email: chachra@tivix.com
License: UNKNOWN
Keywords: django braintree payment
Platform: UNKNOWN
Classifier: Framework :: Django
Classifier: Intended Audience :: Developers
Classifier: Intended Audience :: System Administrators
Classifier: Operating System :: OS Independent
Classifier: Topic :: Software Development
